Metadata-Version: 1.1
Name: plotly-roc
Version: 0.1.0
Summary: interactive roc curves with plotly
Home-page: https://github.com/ayplam/plotly-roc
Author: Adrian Lam
Author-email: ayplam@gmail.com
License: GPLv2
Platform: UNKNOWN
Classifier: Intended Audience :: Developers
Classifier: License :: OSI Approved :: GNU General Public License v2 (GPLv2)
Classifier: Programming Language :: Python :: 3.6
